poepi/__init__.py
poepi/ppi.py
poepi-0.1.2.dist-info/METADATA
poepi-0.1.2.dist-info/WHEEL
poepi-0.1.2.dist-info/RECORD
