Metadata-Version: 2.1
Name: poepi
Version: 0.1.2
Summary: Poepi package
License: MIT
Author: vodovi
Author-email: vodovi4524@crtsec.com
Requires-Python: >=3.10,<4.0
Classifier: License :: OSI Approved :: MIT License
Classifier: Programming Language :: Python :: 3
Classifier: Programming Language :: Python :: 3.10
Classifier: Programming Language :: Python :: 3.11
